Metadata-Version: 1.0
Name: box-box
Version: 0.0.3
Summary: Box of Python Class and Object
Home-page: https://github.com/FebruaryBreeze/box
Author: SF-Zhou
Author-email: sfzhou.scut@gmail.com
License: UNKNOWN
Keywords: Class Object Factory
Platform: UNKNOWN
